{
    "men": [
        {
            "sku": "M100",
            "type": "toupee",
            "durable or natural": "durable",
            "material": "combination",
            "hair type": "straight",
            "url com": "https://www.superhairpieces.com/mens-toupee-m100-6-5x-8-5-mono-top-in-stock/",
            "url ca": "https://superhairpieces.ca/mens-toupee-m100-6-5x-8-5-mono-top-in-stock/",
            "thumbnail": "https://cdn11.bigcommerce.com/s-cavofu/images/stencil/500x659/products/561/12789/M100_Thumb__45901.1631303998.jpg?c=2",
            "product name": "M100 6.5\"x 8.5\" Mono Top"
        },
        {
            "sku": "M100MBSC",
            "type": "toupee",
            "durable or natural": "durable",
            "material": "combination",
            "hair type": "straight",
            "url com": "https://www.superhairpieces.com/mens-toupee-m100-basic-7x-9-mono-top-in-stock-basic-version/",
            "url ca": "https://superhairpieces.ca/mens-toupee-m100-basic-7x-9-mono-top-in-stock-basic-version/",
            "thumbnail": "https://cdn11.bigcommerce.com/s-cavofu/images/stencil/500x659/products/4639/12804/M100B_Thumb__49005.1628285196.jpg?c=2",
            "product name": "M100 Basic 7\"x 9\" Mono Top"
        },
        {
            "sku": "M101",
            "type": "toupee",
            "durable or natural": "durable",
            "material": "skin",
            "hair type": "straight",
            "url com": "https://www.superhairpieces.com/toupee-m101-thin-skin-hair-piece-for-men/",
            "url ca": "https://superhairpieces.ca/toupee-m101-thin-skin-hair-piece-for-men/",
            "thumbnail": "https://cdn11.bigcommerce.com/s-cavofu/images/stencil/500x659/products/437/12791/M101_Thumb__04049.1628021952.jpg?c=2",
            "product name": "M101 8\"x10\" Thin Skin"
        },
        {
            "sku": "M101Perm",
            "type": "toupee",
            "durable or natural": "durable",
            "material": "skin",
            "hair type": "curly",
            "url com": "https://www.superhairpieces.com/m101-permed-wavy-curly-hair-in-stock/",
            "url ca": "https://superhairpieces.ca/m101-permed-wavy-curly-hair-in-stock/",
            "thumbnail": "https://cdn11.bigcommerce.com/s-cavofu/images/stencil/500x659/products/2578/13453/M101P_Thumb__40585.1629405211.jpg?c=2",
            "product name": "M101 8\"x10\" Permed Thin Skin"
        },
        {
            "sku": "M101MBSC",
            "type": "toupee",
            "durable or natural": "durable",
            "material": "skin",
            "hair type": "straight",
            "url com": "https://www.superhairpieces.com/toupee-m101-basic-thin-skin-hair-piece-for-men-basic-version/",
            "url ca": "https://superhairpieces.ca/toupee-m101-basic-thin-skin-hair-piece-for-men-basic-version-m101basic/",
            "thumbnail": "https://cdn11.bigcommerce.com/s-cavofu/images/stencil/500x659/products/4638/12805/M101B_Thumb__90089.1628802832.jpg?c=2",
            "product name": "M101 Basic 7\"x9 Thin Skin"
        },
        {
            "sku": "M102",
            "type": "toupee",
            "durable or natural": "durable",
            "material": "combination",
            "hair type": "straight",
            "url com": "https://www.superhairpieces.com/mens-toupee-m102-8x10-mono-silk-top-lace/",
            "url ca": "https://superhairpieces.ca/mens-toupee-m102-8x10-mono-silk-top-lace/",
            "thumbnail": "https://cdn11.bigcommerce.com/s-cavofu/images/stencil/500x659/products/440/12796/M102_Thumb__86852.1628797720.jpg?c=2",
            "product name": "M102 8\"x10\" Mono Top"
        },
        {
            "sku": "M102LBSC",
            "type": "toupee",
            "durable or natural": "durable",
            "material": "combination",
            "hair type": "straight",
            "url com": "https://www.superhairpieces.com/toupee-m102-basic-8x10-mono-silk-top-lace-basic-version/",
            "url ca": "https://superhairpieces.ca/toupee-m102-basic-8x10-mono-silk-top-lace-basic-version/",
            "thumbnail": "https://cdn11.bigcommerce.com/s-cavofu/images/stencil/500x659/products/3033/12800/M102B_Thumb2__29303.1628287713.jpg?c=2",
            "product name": "M102 Basic 8\"x10\" Mono Top"
        },
        {
            "sku": "M103",
            "type": "toupee",
            "durable or natural": "both",
            "material": "full lace",
            "hair type": "straight",
            "url com": "https://www.superhairpieces.com/mens-toupee-m103-7-5x10-fine-welded-mono-lace-in-stock/",
            "url ca": "https://superhairpieces.ca/mens-toupee-m103-7-5x10-fine-welded-mono-lace-in-stock/",
            "thumbnail": "https://cdn11.bigcommerce.com/s-cavofu/images/stencil/500x659/products/441/13233/M103_Thumb__55136.1628806439.jpg?c=2",
            "product name": "M103 7.5\"x10\" Welded Mono Lace"
        },
        {
            "sku": "M103Afro",
            "type": "toupee",
            "durable or natural": "both",
            "material": "combination",
            "hair type": "straight",
            "url com": "https://www.superhairpieces.com/m103-afro-mens-toupee-mono-top-afro-hairpiece-in-stock/",
            "url ca": "https://superhairpieces.ca/m103-afro-mens-toupee-mono-top-afro-hairpiece-in-stock/",
            "thumbnail": "https://cdn11.bigcommerce.com/s-cavofu/images/stencil/500x659/products/2660/13501/M103A_Thumb__61837.1629407029.jpg?c=2",
            "product name": "M103 Afro 7.5\"x10\" Welded Mono Lace"
        },
        {
            "sku": "M104",
            "type": "toupee",
            "durable or natural": "both",
            "material": "combination",
            "hair type": "straight",
            "url com": "https://www.superhairpieces.com/mens-toupee-m104-7x9-mono-top-with-lace-front-in-stock/",
            "url ca": "https://superhairpieces.ca/mens-toupee-m104-7x9-mono-top-with-lace-front-in-stock/",
            "thumbnail": "https://cdn11.bigcommerce.com/s-cavofu/images/stencil/500x659/products/439/13253/M104_Thumb__68958.1628889152.jpg?c=2",
            "product name": "M104 7\"x9\" Mono Top with Lace Front"
        },
        {
            "sku": "M104MBSC",
            "type": "toupee",
            "durable or natural": "both",
            "material": "combination",
            "hair type": "straight",
            "url com": "https://www.superhairpieces.com/toupee-m104-monofilament-lace-top-with-natural-hair-line-basic-version/",
            "url ca": "https://superhairpieces.ca/toupee-m104-monofilament-lace-top-with-natural-hair-line-basic-version/",
            "thumbnail": "https://cdn11.bigcommerce.com/s-cavofu/images/stencil/500x659/products/5014/13414/M104B_1__71701.1629396815.jpg?c=2",
            "product name": "M104 Basic 7\"x9\" Mono Top with Lace Front"
        },
        {
            "sku": "M104Perm",
            "type": "toupee",
            "durable or natural": "both",
            "material": "combination",
            "hair type": "curly",
            "url com": "https://www.superhairpieces.com/m104-permed-wavy-curly-hair-in-stock/",
            "url ca": "https://superhairpieces.ca/m104-permed-wavy-curly-hair-in-stock/",
            "thumbnail": "https://cdn11.bigcommerce.com/s-cavofu/images/stencil/500x659/products/2579/12823/M104P_Thumb__73391.1628026193.jpg?c=2",
            "product name": "M104 Permed 7\"x9\" Mono Top with Lace Front"
        },
        {
            "sku": "M105",
            "type": "toupee",
            "durable or natural": "natural-looking",
            "material": "full lace",
            "hair type": "straight",
            "url com": "https://www.superhairpieces.com/mens-toupee-m105-8x-10-french-lace-in-stock/",
            "url ca": "https://superhairpieces.ca/mens-toupee-m105-8x-10-french-lace-in-stock/",
            "thumbnail": "https://cdn11.bigcommerce.com/s-cavofu/images/stencil/500x659/products/453/13402/M105_Thumb__57841.1629392362.jpg?c=2",
            "product name": "M105 8\"x10\" Full French Lace"
        },
        {
            "sku": "HD105",
            "type": "toupee",
            "durable or natural": "natural-looking",
            "material": "full lace",
            "hair type": "straight",
            "url com": "https://www.superhairpieces.com/hd105-m135-8-x-10-french-lace-in-stock/",
            "url ca": "https://superhairpieces.ca/hd105-m135-8-x-10-french-lace-in-stock/",
            "thumbnail": "https://cdn11.bigcommerce.com/s-cavofu/images/stencil/500x659/products/1185/13403/HD105_Thumb__14775.1629407999.jpg?c=2",
            "product name": "HD105 8\"x10\" Full French Lace"
        },
        {
            "sku": "HD105Perm",
            "type": "toupee",
            "durable or natural": "natural-looking",
            "material": "full lace",
            "hair type": "curly",
            "url com": "https://www.superhairpieces.com/hd105perm",
            "url ca": "https://superhairpieces.ca/hd105perm",
            "thumbnail": "https://cdn11.bigcommerce.com/s-cavofu/images/stencil/500x659/products/1880/13302/HD105P_1__57149.1629145656.jpg?c=2",
            "product name": "HD105 8\"x10\" Permed Full French Lace"
        },
        {
            "sku": "M106",
            "type": "toupee",
            "durable or natural": "natural-looking",
            "material": "combination",
            "hair type": "straight",
            "url com": "https://www.superhairpieces.com/mens-toupee-m106-6-5x8-5-french-lace-poly-back-in-stock/",
            "url ca": "https://superhairpieces.ca/mens-toupee-m106-6-5x8-5-french-lace-poly-back-in-stock/",
            "thumbnail": "https://cdn11.bigcommerce.com/s-cavofu/images/stencil/500x659/products/499/14454/M106_Thumb__15566.1629408698222__13879.1636229827.jpg?c=2",
            "product name": "M106 6.5\"x8.5\" French Lace with Poly Back"
        },
        {
            "sku": "M106L",
            "type": "toupee",
            "durable or natural": "natural-looking",
            "material": "combination",
            "hair type": "straight",
            "url com": "https://www.superhairpieces.com/mens-toupee-m106l-8x10-french-lace-poly-back-in-stock/",
            "url ca": "https://superhairpieces.ca/mens-toupee-m106l-8x10-french-lace-poly-back-in-stock/",
            "thumbnail": "https://cdn11.bigcommerce.com/s-cavofu/images/stencil/500x659/products/1881/14455/M106L_Thumb__68378.1630701196222__04544.1636229864.jpg?c=2",
            "product name": "M106L 8\"x10\" French Lace with Poly Back"
        },
        {
            "sku": "M107",
            "type": "toupee",
            "durable or natural": "natural-looking",
            "material": "combination",
            "hair type": "straight",
            "url com": "https://www.superhairpieces.com/mens-toupee-m107-7-5x9-5-fw-mono-lace-pu-back-in-stock/",
            "url ca": "https://superhairpieces.ca/mens-toupee-m107-7-5x9-5-fw-mono-lace-pu-back-in-stock/",
            "thumbnail": "https://cdn11.bigcommerce.com/s-cavofu/images/stencil/500x659/products/451/12854/M107_Thumb__31438.1628106430.jpg?c=2",
            "product name": "M107 7.5\"x9.5\" Fine Welded Mono Lace with Poly Back"
        },
        {
            "sku": "M107",
            "type": "toupee",
            "durable or natural": "natural-looking",
            "material": "combination",
            "hair type": "straight",
            "url com": "https://www.superhairpieces.com/mens-toupee-m107-7-5x9-5-fw-mono-lace-pu-back-in-stock/",
            "url ca": "https://superhairpieces.ca/mens-toupee-m107-7-5x9-5-fw-mono-lace-pu-back-in-stock/",
            "thumbnail": "https://cdn11.bigcommerce.com/s-cavofu/images/stencil/500x659/products/451/12854/M107_Thumb__31438.1628106430.jpg?c=2",
            "product name": "M107 7.5\"x9.5\" Fine Welded Mono Lace with Poly Back"
        },
        {
            "sku": "M108",
            "type": "toupee",
            "durable or natural": "durable",
            "material": "combination",
            "hair type": "straight",
            "url com": "https://www.superhairpieces.com/mens-toupee-m108-8x10-human-hair-mono-top-in-stock/",
            "url ca": "https://superhairpieces.ca/mens-toupee-m108-8x10-human-hair-mono-top-in-stock/",
            "thumbnail": "https://cdn11.bigcommerce.com/s-cavofu/images/stencil/500x659/products/480/13405/M108_Thumb__04044.1631726186.jpg?c=2",
            "product name": "M108 8\"x10\" Mono Top with Poly Back"
        },
        {
            "sku": "M108CC",
            "type": "toupee",
            "durable or natural": "durable",
            "material": "combination",
            "hair type": "straight",
            "url com": "https://www.superhairpieces.com/cc-shape-wider-front-hairline-m108-8x10-mono-top-hair-in-stock/",
            "url ca": "https://superhairpieces.ca/cc-shape-wider-front-hairline-m108-8x10-mono-top-hair-in-stock/",
            "thumbnail": "https://cdn11.bigcommerce.com/s-cavofu/images/stencil/500x659/products/1889/13407/M108CC_Thumb__48956.1631730855.jpg?c=2",
            "product name": "M108CC 8\"x10\" Mono Top"
        },
        {
            "sku": "M108Perm",
            "type": "toupee",
            "durable or natural": "durable",
            "material": "combination",
            "hair type": "curly",
            "url com": "https://www.superhairpieces.com/m108-permed-wavy-curly-hair-in-stock/",
            "url ca": "https://superhairpieces.ca/m108-permed-wavy-curly-hair-in-stock/",
            "thumbnail": "https://cdn11.bigcommerce.com/s-cavofu/images/stencil/500x659/products/2580/13408/M108P_1__87732.1629396058.jpg?c=2",
            "product name": "M108 Permed 8\"x10\" Mono Top"
        },
        {
            "sku": "M108Afro",
            "type": "toupee",
            "durable or natural": "durable",
            "material": "combination",
            "hair type": "curly",
            "url com": "https://www.superhairpieces.com/m108-afro-mens-toupee-8x10-mono-top-afro-hairpiece-in-stock/",
            "url ca": "https://superhairpieces.ca/m108-afro-mens-toupee-8x10-mono-top-afro-hairpiece-in-stock/",
            "thumbnail": "https://cdn11.bigcommerce.com/s-cavofu/images/stencil/500x659/products/671/13426/M108A_Thumb__71773.1629400580.jpg?c=2",
            "product name": "M108 Afro 8\"x10\" Mono Top"
        },
        {
            "sku": "M108MBSC",
            "type": "toupee",
            "durable or natural": "durable",
            "material": "combination",
            "hair type": "straight",
            "url com": "https://www.superhairpieces.com/mens-toupee-m108-basic-7-5x9-human-hair-mono-top-in-stock-basic-version/",
            "url ca": "https://superhairpieces.ca/mens-toupee-m108-basic-7x9-human-hair-mono-top-in-stock-basic-version-m108basic/",
            "thumbnail": "https://cdn11.bigcommerce.com/s-cavofu/images/stencil/500x659/products/4640/13406/M108B_Thumb__54435.1631728914.jpg?c=2",
            "product name": "M108 Basic 7.5\"x9\" Mono Top"
        },
        {
            "sku": "M108MBSC",
            "type": "toupee",
            "durable or natural": "durable",
            "material": "combination",
            "hair type": "straight",
            "url com": "https://www.superhairpieces.com/mens-toupee-m108-basic-7-5x9-human-hair-mono-top-in-stock-basic-version/",
            "url ca": "https://superhairpieces.ca/mens-toupee-m108-basic-7x9-human-hair-mono-top-in-stock-basic-version-m108basic/",
            "thumbnail": "https://cdn11.bigcommerce.com/s-cavofu/images/stencil/500x659/products/4640/13406/M108B_Thumb__54435.1631728914.jpg?c=2",
            "product name": "M108 Basic 7.5\"x9\" Mono Top"
        },
        {
            "sku": "M109",
            "type": "toupee",
            "durable or natural": "both",
            "material": "combination",
            "hair type": "straight",
            "url com": "https://www.superhairpieces.com/mens-toupee-m109-8x10-mono-top-lace-front-in-stock/",
            "url ca": "https://superhairpieces.ca/mens-toupee-m109-8x10-mono-top-lace-front-in-stock/",
            "thumbnail": "https://cdn11.bigcommerce.com/s-cavofu/images/stencil/500x659/products/501/13876/M109_Thumb__85802.1632241696.jpg?c=2",
            "product name": "M109 8\"x10\" Mono Top Lace Front"
        },
        {
            "sku": "M109LBSC",
            "type": "toupee",
            "durable or natural": "both",
            "material": "combination",
            "hair type": "straight",
            "url com": "https://www.superhairpieces.com/mens-toupee-m109-8x10-mono-top-lace-front-basic-version/",
            "url ca": "https://superhairpieces.ca/mens-toupee-m109-8x10-mono-top-lace-front-basic-version/",
            "thumbnail": "https://cdn11.bigcommerce.com/s-cavofu/images/stencil/500x659/products/6065/14307/M109B_thumb__99896.1634934484.jpg?c=2",
            "product name": "M109 Basic 8\"x10\" Mono Top Lace Front"
        },
        {
            "sku": "M110",
            "type": "toupee",
            "durable or natural": "natural-looking",
            "material": "full lace",
            "hair type": "straight",
            "url com": "https://www.superhairpieces.com/mens-toupee-m110-super-fine-welded-lace-mens-hairpiece-in-stock/",
            "url ca": "https://superhairpieces.ca/mens-toupee-m110-super-fine-welded-lace-mens-hairpiece-in-stock/",
            "thumbnail": "https://cdn11.bigcommerce.com/s-cavofu/images/stencil/500x659/products/512/13880/M110_Thumb__68515.1631738712.jpg?c=2",
            "product name": "M110 8\"x10\" Super Fine Welded Lace"
        },
        {
            "sku": "M110L",
            "type": "toupee",
            "durable or natural": "natural-looking",
            "material": "full lace",
            "hair type": "straight",
            "url com": "https://www.superhairpieces.com/m110l-mens-toupee-7-5x-9-5-super-fine-welded-lace-in-stock/",
            "url ca": "https://superhairpieces.ca/m110l-mens-toupee-7-5x-9-5-super-fine-welded-lace-in-stock/",
            "thumbnail": "https://cdn11.bigcommerce.com/s-cavofu/images/stencil/500x659/products/869/13881/M110L_Thumb__29140.1631739128.jpg?c=2",
            "product name": "M110L 7.5\"x 9.5\" Super Fine Welded Lace"
        },
        {
            "sku": "M111",
            "type": "toupee",
            "durable or natural": "natural-looking",
            "material": "skin",
            "hair type": "straight",
            "url com": "https://www.superhairpieces.com/mens-toupee-m111-8x10-thinnest-skin-base-hairpiece-disposable/",
            "url ca": "https://superhairpieces.ca/mens-toupee-m111-8x10-thinnest-skin-base-hairpiece-disposable/",
            "thumbnail": "https://cdn11.bigcommerce.com/s-cavofu/images/stencil/500x659/products/633/13878/M111_Thumb__17827.1631742271.jpg?c=2",
            "product name": "M111 8\"x10\" Thinnest Skin Base Hairpiece Disposable"
        },
        {
            "sku": "HD111",
            "type": "toupee",
            "durable or natural": "natural-looking",
            "material": "skin",
            "hair type": "straight",
            "url com": "https://www.superhairpieces.com/mens-toupee-hd111-8x10-thinnest-skin-base-hairpiece-disposable/",
            "url ca": "https://superhairpieces.ca/mens-toupee-hd111-8x10-thinnest-skin-base-hairpiece-disposable/",
            "thumbnail": "https://cdn11.bigcommerce.com/s-cavofu/images/stencil/500x659/products/1294/13879/HD111_Thumb__13860.1631740848.jpg?c=2",
            "product name": "HD111 8\"x10\" Thinnest Skin Base Hairpiece Disposable"
        },
        {
            "sku": "M112",
            "type": "toupee",
            "durable or natural": "durable",
            "material": "combination",
            "hair type": "straight",
            "url com": "https://www.superhairpieces.com/mens-toupee-m112-6x8-mono-top-mens-toupee-in-stock/",
            "url ca": "https://superhairpieces.ca/mens-toupee-m112-6x8-mono-top-mens-toupee-in-stock/",
            "thumbnail": "https://cdn11.bigcommerce.com/s-cavofu/images/stencil/500x659/products/595/13877/M112_Thumb__39991.1632169304.jpg?c=2",
            "product name": "M112 6\"x8\" Mono Top"
        },
        {
            "sku": "M112SBSC",
            "type": "toupee",
            "durable or natural": "durable",
            "material": "combination",
            "hair type": "straight",
            "url com": "https://www.superhairpieces.com/mens-toupee-m112-basic-6x8-mono-top-mens-toupee-in-stock-basic-version/",
            "url ca": "https://superhairpieces.ca/mens-toupee-m112-basic-6x8-mono-top-mens-toupee-in-stock-basic-version/",
            "thumbnail": "https://cdn11.bigcommerce.com/s-cavofu/images/stencil/500x659/products/3039/13882/M112B_Thumb__23957.1632171244.jpg?c=2",
            "product name": "M112 Basic 6\"x8\" Mono Top"
        },
        {
            "sku": "M115",
            "type": "toupee",
            "durable or natural": "natural-looking",
            "material": "full lace",
            "hair type": "straight",
            "url com": "https://www.superhairpieces.com/mens-toupee-m115-8x10-swiss-lace-low-density-toupee/",
            "url ca": "https://superhairpieces.ca/mens-toupee-m115-8x10-swiss-lace-low-density-toupee/",
            "thumbnail": "https://cdn11.bigcommerce.com/s-cavofu/images/stencil/500x659/products/739/13887/M115_Thumb__11899.1632243559.jpg?c=2",
            "product name": "M115 8\"x10\" Full Swiss Lace"
        },
        {
            "sku": "M116S",
            "type": "toupee",
            "durable or natural": "natural-looking",
            "material": "full lace",
            "hair type": "straight",
            "url com": "https://www.superhairpieces.com/mens-toupee-m116s-6x8-swiss-lace-poly-back-in-stock-mens-hairpiece/",
            "url ca": "https://superhairpieces.ca/mens-toupee-m116s-6x8-swiss-lace-poly-back-in-stock-mens-hairpiece/",
            "thumbnail": "https://cdn11.bigcommerce.com/s-cavofu/images/stencil/500x659/products/766/13883/M116S_Thumb__87271.1632333940.jpg?c=2",
            "product name": "M116S 6\"x8\" Swiss Lace Poly Back"
        },
        {
            "sku": "M116M",
            "type": "toupee",
            "durable or natural": "natural-looking",
            "material": "full lace",
            "hair type": "straight",
            "url com": "https://www.superhairpieces.com/mens-toupee-m116m-7x9-swiss-lace-poly-back-in-stock-mens-hairpiece/",
            "url ca": "https://superhairpieces.ca/mens-toupee-m116m-7x9-swiss-lace-poly-back-in-stock-mens-hairpiece/",
            "thumbnail": "https://cdn11.bigcommerce.com/s-cavofu/images/stencil/500x659/products/767/13884/M116M_Thumb__10276.1632246630.jpg?c=2",
            "product name": "M116M 7\"x9\" Swiss Lace Poly Back"
        },
        {
            "sku": "M116L",
            "type": "toupee",
            "durable or natural": "natural-looking",
            "material": "full lace",
            "hair type": "straight",
            "url com": "https://www.superhairpieces.com/mens-toupee-m116l-8x10-swiss-lace-poly-back-in-stock-mens-hairpiece/",
            "url ca": "https://superhairpieces.ca/mens-toupee-m116l-8x10-swiss-lace-poly-back-in-stock-mens-hairpiece/",
            "thumbnail": "https://cdn11.bigcommerce.com/s-cavofu/images/stencil/500x659/products/795/13885/M116L_Thumb__56647.1632329762.jpg?c=2",
            "product name": "M116L 8\"x10\" Swiss lace poly back"
        },
        {
            "sku": "M158",
            "type": "toupee",
            "durable or natural": "durable",
            "material": "combination",
            "hair type": "straight",
            "url com": "https://www.superhairpieces.com/m158-mens-toupee-8x-10-human-hair-skin-base-lace-top-in-stock/",
            "url ca": "https://superhairpieces.ca/m158-mens-toupee-8x-10-human-hair-skin-base-lace-top-in-stock/",
            "thumbnail": "https://cdn11.bigcommerce.com/s-cavofu/images/stencil/500x659/products/1181/13889/M158_Thumb__26927.1631288383.jpg?c=2",
            "product name": "M158 8\"x 10\" Skin Base French Lace Top"
        },
        {
            "sku": "M258",
            "type": "toupee",
            "durable or natural": "durable",
            "material": "combination",
            "hair type": "straight",
            "url com": "https://www.superhairpieces.com/m258-mens-toupee-8x-10-human-hair-skin-base-mono-lace-top-in-stock/",
            "url ca": "https://superhairpieces.ca/m258-mens-toupee-8x-10-human-hair-skin-base-mono-top-in-stock/",
            "thumbnail": "https://cdn11.bigcommerce.com/s-cavofu/images/stencil/500x659/products/5121/13892/M258_Thumb__56358.1631288706.jpg?c=2",
            "product name": "M258 8\"x 10\" Human Hair Skin Base Mono Top"
        },
        {
            "sku": "M159",
            "type": "toupee",
            "durable or natural": "durable",
            "material": "combination",
            "hair type": "straight",
            "url com": "https://www.superhairpieces.com/mens-toupee-m159-8x10-human-hair-lace-top-hairpiece-stock/",
            "url ca": "https://superhairpieces.ca/mens-toupee-m159-8x10-human-hair-lace-top-hairpiece-stock/",
            "thumbnail": "https://cdn11.bigcommerce.com/s-cavofu/images/stencil/500x659/products/1317/13893/M159_Thumb__80309.1631289779.jpg?c=2",
            "product name": "M159 8\"x10\" Lace Top"
        },
        {
            "sku": "M161",
            "type": "toupee",
            "durable or natural": "both",
            "material": "skin",
            "hair type": "straight",
            "url com": "https://www.superhairpieces.com/m161-mens-toupee-8x10-poly-skin-invisible-knot-mens-hair-system/",
            "url ca": "https://superhairpieces.ca/m161-mens-toupee-8x10-poly-skin-invisible-knot-mens-hair-system/",
            "thumbnail": "https://cdn11.bigcommerce.com/s-cavofu/images/stencil/500x659/products/1047/13894/M161_Thumb__12187.1631290004.jpg?c=2",
            "product name": "M161 8\"x10\" Poly Skin Lace Front"
        },
        {
            "sku": "M161V",
            "type": "toupee",
            "durable or natural": "natural-looking",
            "material": "skin",
            "hair type": "straight",
            "url com": "https://www.superhairpieces.com/m161v-mens-toupee-8x10-poly-skin-v-loop-mens-hair-system/",
            "url ca": "https://superhairpieces.ca/m161v-mens-toupee-8x10-poly-skin-v-loop-mens-hair-system/",
            "thumbnail": "https://cdn11.bigcommerce.com/s-cavofu/images/stencil/500x659/products/5086/13895/M161V_Thumb__06872.1631299413.jpg?c=2",
            "product name": "M161V 8\"x10\" Poly Skin Lace Front V Loop"
        },
        {
            "sku": "W1",
            "type": "full cap",
            "durable or natural": "durable",
            "material": "skin",
            "hair type": "straight",
            "url com": "https://www.superhairpieces.com/in-stock-mens-full-cap-top-hand-made-human-hair-wig-w1/",
            "url ca": "https://superhairpieces.ca/in-stock-mens-full-cap-top-hand-made-human-hair-wig-w1/",
            "thumbnail": "https://cdn11.bigcommerce.com/s-cavofu/images/stencil/500x659/products/5230/12334/W1__46892.1622650445.jpg?c=2",
            "product name": "W1 Mens Wig Skin Base"
        },
        {
            "sku": "W8",
            "type": "full cap",
            "durable or natural": "durable",
            "material": "combination",
            "hair type": "straight",
            "url com": "https://www.superhairpieces.com/in-stock-mens-full-cap-silk-top-hand-made-human-hair-wig-w8/",
            "url ca": "https://superhairpieces.ca/in-stock-mens-full-cap-silk-top-hand-made-human-hair-wig-w8/",
            "thumbnail": "https://cdn11.bigcommerce.com/s-cavofu/images/stencil/500x659/products/1247/13896/W8_Thumb__15724.1632413733.jpg?c=2",
            "product name": "W8 Mens Wig Silk mono lace with clear skin perimeter and cross crown"
        }
    ]
}